alto/__init__.py
alto/__main__.py
alto/catalog.py
alto/config.py
alto/constants.py
alto/dlt_singer.py
alto/engine.py
alto/ext/__init__.py
alto/ext/evidence.py
alto/ext/rill.py
alto/incl/alto.local.template.json
alto/incl/alto.local.template.toml
alto/incl/alto.local.template.yaml
alto/incl/alto.template.json
alto/incl/alto.template.toml
alto/incl/alto.template.yaml
alto/incl/bls-series.json
alto/incl/dlt_example.py
alto/logger.py
alto/main.py
alto/models.py
alto/providers/__init__.py
alto/providers/serde.py
alto/repl.py
alto/state.py
alto/tools.py
alto/ui.py
alto/utils.py
alto/version.py
singer_alto-0.2.21.dist-info/LICENSE
singer_alto-0.2.21.dist-info/entry_points.txt
singer_alto-0.2.21.dist-info/WHEEL
singer_alto-0.2.21.dist-info/METADATA
singer_alto-0.2.21.dist-info/RECORD
