Metadata-Version: 2.1
Name: singer-alto
Version: 0.2.21
Summary: A package for managing singer.io taps and targets
Home-page: https://github.com/z3z1ma/alto
License: MIT
Keywords: alto,singer,tap,target,etl,data,pipeline
Author: z3z1ma
Author-email: butler.alex2010@gmail.com
Requires-Python: >=3.8,<3.12
Classifier: Development Status :: 4 - Beta
Classifier: Environment :: Console
Classifier: Intended Audience :: Developers
Classifier: License :: OSI Approved :: MIT License
Classifier: Natural Language :: English
Classifier: Operating System :: OS Independent
Classifier: Programming Language :: Python :: 3
Classifier: Programming Language :: Python :: 3.8
Classifier: Programming Language :: Python :: 3.9
Classifier: Programming Language :: Python :: 3.10
Classifier: Programming Language :: Python :: 3.11
Classifier: Programming Language :: Python :: 3.10
Classifier: Programming Language :: Python :: 3.11
Classifier: Programming Language :: Python :: 3.8
Classifier: Programming Language :: Python :: 3.9
Classifier: Topic :: Software Development :: Libraries :: Python Modules
Requires-Dist: doit (>=0.36.0)
Requires-Dist: dynaconf (>=3.1.11,<4.0.0)
Requires-Dist: fsspec (>=2023.1.0,<2024.0.0)
Requires-Dist: pex (>=2)
Project-URL: Documentation, https://z3z1ma.github.io/alto/
Project-URL: Repository, https://github.com/z3z1ma/alto
